{"has_registered_address": false, "name": "SNOWFLAKE INC.", "agent_name": "NATIONAL REGISTERED AGENTS, INC", "registered_address": "160 GREENTREE DR STE 101, DOVER, Kent, DE, 19904", "company_number": "5185958", "jurisdiction_code": "us_de", "incorporation_date": "2012-07-23", "registry_url": "https://icis.corp.delaware.gov/Ecorp/EntitySearch/NameSearch.aspx", "source": {"publisher": "Delaware Department of State: Division of Corporations", "url": "http://www.corp.delaware.gov/", "retrieved_at": "2019-08-31T15:29:38+00:00"}, "opencorporates_url": "https://opencorporates.com/companies/us_de/5185958", "officers": [{"officer": {"id": 160619953, "name": "NATIONAL REGISTERED AGENTS, INC", "position": "agent", "uid": null, "start_date": null, "end_date": null, "opencorporates_url": "https://opencorporates.com/officers/160619953", "occupation": null, "inactive": null, "current_status": null, "address": "160 GREENTREE DR STE 101, DOVER, Kent, DE, 19904", "nationality": null, "date_of_birth": null}}]}